multi_file/__init__.py
multi_file-0.0.1.dist-info/LICENSE
multi_file-0.0.1.dist-info/METADATA
multi_file-0.0.1.dist-info/WHEEL
multi_file-0.0.1.dist-info/top_level.txt
multi_file-0.0.1.dist-info/RECORD
