Metadata-Version: 2.1
Name: multi-file
Version: 0.0.1
Summary: put multiple fileobjs inside a fileobj
Home-page: UNKNOWN
Author: Casey Marks
Author-email: casey@carveacre.com
License: UNKNOWN
Platform: UNKNOWN
Classifier: Programming Language :: Python :: 3
Classifier: License :: OSI Approved :: MIT License
Classifier: Operating System :: OS Independent
Requires-Python: >=3.6
